tracardi_postgresql_connector/plugin.py
tracardi_postgresql_connector/model/configuration.py
tracardi_postgresql_connector/model/postresql.py
tracardi_postgresql_connector/model/__pycache__/configuration.cpython-38.pyc
tracardi_postgresql_connector/model/__pycache__/postresql.cpython-38.pyc
tracardi_postgresql_connector-0.6.0.dist-info/LICENSE.md
tracardi_postgresql_connector-0.6.0.dist-info/METADATA
tracardi_postgresql_connector-0.6.0.dist-info/WHEEL
tracardi_postgresql_connector-0.6.0.dist-info/top_level.txt
tracardi_postgresql_connector-0.6.0.dist-info/RECORD
